pyurlcheck/__init__.py
pyurlcheck/check.py
pyurlcheck/cli.py
pyurlcheck/constants.py
pyurlcheck/find.py
pyurlcheck/utils.py
pyurlcheck/validate.py
pyurlcheck-0.1.2.dist-info/entry_points.txt
pyurlcheck-0.1.2.dist-info/WHEEL
pyurlcheck-0.1.2.dist-info/METADATA
pyurlcheck-0.1.2.dist-info/RECORD
