Metadata-Version: 2.1
Name: pyurlcheck
Version: 0.1.2
Summary: Search docs and validate URLs found are working properly.
Home-page: https://github.com/jeffkala/pyurlcheck.git
License: MIT
Author: Jeff Kala
Author-email: jeff.l.kala@gmail.com
Requires-Python: >=3.6,<4.0
Classifier: License :: OSI Approved :: MIT License
Classifier: Programming Language :: Python :: 3
Classifier: Programming Language :: Python :: 3.6
Classifier: Programming Language :: Python :: 3.7
Classifier: Programming Language :: Python :: 3.8
Classifier: Programming Language :: Python :: 3.9
Requires-Dist: click (>=7.1.2,<8.0.0)
Requires-Dist: dnspython (>=2.1.0,<3.0.0)
Requires-Dist: requests (>=2.25.1,<3.0.0)
Project-URL: Repository, https://github.com/jeffkala/pyurlcheck.git
